LICENSE
MANIFEST.in
README.md
setup.cfg
setup.py
django_incident_response.egg-info/PKG-INFO
django_incident_response.egg-info/SOURCES.txt
django_incident_response.egg-info/dependency_links.txt
django_incident_response.egg-info/requires.txt
django_incident_response.egg-info/top_level.txt
response/__init__.py
response/admin.py
response/apps.py
response/decorators.py
response/errors.py
response/models.py
response/serializers.py
response/urls.py
response/core/__init__.py
response/core/admin.py
response/core/serializers.py
response/core/signals.py
response/core/urls.py
response/core/util.py
response/core/views.py
response/core/models/__init__.py
response/core/models/action.py
response/core/models/event.py
response/core/models/incident.py
response/core/models/timeline.py
response/core/models/user_external.py
response/migrations/0001_initial.py
response/migrations/0002_timelineevent.py
response/migrations/0003_auto_20190904_1349.py
response/migrations/0004_auto_20190904_1704.py
response/migrations/0005_auto_20190906_1413.py
response/migrations/0006_externaluser_full_name.py
response/migrations/0007_delete_incidentextension.py
response/migrations/0008_externaluser_email.py
response/migrations/0009_commschannel_channel_name.py
response/migrations/0010_incident_report_only.py
response/migrations/0011_auto_20190927_1339.py
response/migrations/0012_commschannel_onetoone.py
response/migrations/0013_incident_private.py
response/migrations/0014_event.py
response/migrations/0015_improve_actions.py
response/migrations/0016_actions_auto_created_date.py
response/migrations/__init__.py
response/slack/__init__.py
response/slack/action_handlers.py
response/slack/admin.py
response/slack/authentication.py
response/slack/block_kit.py
response/slack/cache.py
response/slack/client.py
response/slack/dialog_builder.py
response/slack/dialog_handlers.py
response/slack/event_handlers.py
response/slack/incident_notifications.py
response/slack/reference_utils.py
response/slack/settings.py
response/slack/signals.py
response/slack/urls.py
response/slack/views.py
response/slack/decorators/__init__.py
response/slack/decorators/action_handler.py
response/slack/decorators/dialog_handler.py
response/slack/decorators/event_handler.py
